odoo10_addon_mgmtsystem_hazard_risk-10.0.1.1.0.99.dev4-nspkg.pth
odoo/addons/mgmtsystem_hazard_risk/README.rst
odoo/addons/mgmtsystem_hazard_risk/__init__.py
odoo/addons/mgmtsystem_hazard_risk/__manifest__.py
odoo/addons/mgmtsystem_hazard_risk/data/mgmtsystem_hazard_risk_computation.xml
odoo/addons/mgmtsystem_hazard_risk/data/mgmtsystem_hazard_risk_type.xml
odoo/addons/mgmtsystem_hazard_risk/i18n/de.po
odoo/addons/mgmtsystem_hazard_risk/i18n/es.po
odoo/addons/mgmtsystem_hazard_risk/i18n/fr.po
odoo/addons/mgmtsystem_hazard_risk/i18n/hr.po
odoo/addons/mgmtsystem_hazard_risk/i18n/id.po
odoo/addons/mgmtsystem_hazard_risk/i18n/mgmtsystem_hazard_risk.pot
odoo/addons/mgmtsystem_hazard_risk/i18n/nb.po
odoo/addons/mgmtsystem_hazard_risk/i18n/pt_BR.po
odoo/addons/mgmtsystem_hazard_risk/i18n/sl.po
odoo/addons/mgmtsystem_hazard_risk/i18n/vi.po
odoo/addons/mgmtsystem_hazard_risk/models/__init__.py
odoo/addons/mgmtsystem_hazard_risk/models/common.py
odoo/addons/mgmtsystem_hazard_risk/models/mgmtsystem_hazard.py
odoo/addons/mgmtsystem_hazard_risk/models/mgmtsystem_hazard_residual_risk.py
odoo/addons/mgmtsystem_hazard_risk/models/mgmtsystem_hazard_risk_computation.py
odoo/addons/mgmtsystem_hazard_risk/models/mgmtsystem_hazard_risk_type.py
odoo/addons/mgmtsystem_hazard_risk/models/res_company.py
odoo/addons/mgmtsystem_hazard_risk/security/ir.model.access.csv
odoo/addons/mgmtsystem_hazard_risk/security/mgmtsystem_hazard_security.xml
odoo/addons/mgmtsystem_hazard_risk/static/description/icon.png
odoo/addons/mgmtsystem_hazard_risk/tests/__init__.py
odoo/addons/mgmtsystem_hazard_risk/tests/test_mgmtsystem_hazard.py
odoo/addons/mgmtsystem_hazard_risk/views/mgmtsystem_hazard.xml
odoo/addons/mgmtsystem_hazard_risk/views/mgmtsystem_hazard_residual_risk.xml
odoo/addons/mgmtsystem_hazard_risk/views/mgmtsystem_hazard_risk_computation.xml
odoo/addons/mgmtsystem_hazard_risk/views/mgmtsystem_hazard_risk_type.xml
odoo/addons/mgmtsystem_hazard_risk/views/res_company.xml
odoo10_addon_mgmtsystem_hazard_risk-10.0.1.1.0.99.dev4.dist-info/METADATA
odoo10_addon_mgmtsystem_hazard_risk-10.0.1.1.0.99.dev4.dist-info/WHEEL
odoo10_addon_mgmtsystem_hazard_risk-10.0.1.1.0.99.dev4.dist-info/namespace_packages.txt
odoo10_addon_mgmtsystem_hazard_risk-10.0.1.1.0.99.dev4.dist-info/top_level.txt
odoo10_addon_mgmtsystem_hazard_risk-10.0.1.1.0.99.dev4.dist-info/RECORD
